biovector/KO_programs.py
biovector/__init__.py
biovector/__main__.py
biovector/bv_utils.py
biovector/config.yaml
biovector/interactive.py
biovector/printbv.py
biovector/stats.py
biovector/workout.py
biovector/data/.swap.csv
biovector/data/exercises.csv
biovector/data/sets (conflict 2022-04-21-01-16-13).csv
biovector/data/sets.csv
biovector/data/workouts.csv
biovector/data/programs/531.yaml
biovector/data/programs/monolith.yaml
biovector-0.0.0.dist-info/LICENSE
biovector-0.0.0.dist-info/METADATA
biovector-0.0.0.dist-info/WHEEL
biovector-0.0.0.dist-info/top_level.txt
biovector-0.0.0.dist-info/RECORD
